citadel_workspace/__init__.py
citadel_workspace/citadel_workspace.py
citadel_workspace-0.1.0.dist-info/METADATA
citadel_workspace-0.1.0.dist-info/WHEEL
citadel_workspace-0.1.0.dist-info/RECORD
