Metadata-Version: 2.1
Name: citadel-workspace
Version: 0.1.0
Summary: List and select workspace from citadel terraform customers.
Author: Bruno da Silva Valenga
Author-email: brunodasilvalenga@gmail.com
Requires-Python: >=3.11,<4.0
Classifier: Programming Language :: Python :: 3
Classifier: Programming Language :: Python :: 3.11
